odoo/addons/mrp_production_picking_type_from_route/README.rst
odoo/addons/mrp_production_picking_type_from_route/__init__.py
odoo/addons/mrp_production_picking_type_from_route/__manifest__.py
odoo/addons/mrp_production_picking_type_from_route/i18n/it.po
odoo/addons/mrp_production_picking_type_from_route/i18n/mrp_production_picking_type_from_route.pot
odoo/addons/mrp_production_picking_type_from_route/i18n/nl.po
odoo/addons/mrp_production_picking_type_from_route/models/__init__.py
odoo/addons/mrp_production_picking_type_from_route/models/mrp_production.py
odoo/addons/mrp_production_picking_type_from_route/readme/CONTRIBUTORS.md
odoo/addons/mrp_production_picking_type_from_route/readme/DESCRIPTION.md
odoo/addons/mrp_production_picking_type_from_route/readme/USAGE.md
odoo/addons/mrp_production_picking_type_from_route/static/description/icon.png
odoo/addons/mrp_production_picking_type_from_route/static/description/index.html
odoo/addons/mrp_production_picking_type_from_route/tests/__init__.py
odoo/addons/mrp_production_picking_type_from_route/tests/test_mrp_production_picking_type_from_route.py
odoo_addon_mrp_production_picking_type_from_route-18.0.1.0.0.2.dist-info/METADATA
odoo_addon_mrp_production_picking_type_from_route-18.0.1.0.0.2.dist-info/WHEEL
odoo_addon_mrp_production_picking_type_from_route-18.0.1.0.0.2.dist-info/top_level.txt
odoo_addon_mrp_production_picking_type_from_route-18.0.1.0.0.2.dist-info/RECORD
